LICENSE.md
ftt/__init__.py
ftt/__main__.py
ftt/application.py
ftt/cli/__init__.py
ftt/cli/application_config_dto.py
ftt/cli/commands/__init__.py
ftt/cli/commands/example_commands.py
ftt/cli/commands/portfolio_versions_commands.py
ftt/cli/commands/portfolios_commands.py
ftt/cli/context.py
ftt/cli/handlers/__init__.py
ftt/cli/handlers/create_portfolio_prompts_handler.py
ftt/cli/handlers/define_example_config_path_step.py
ftt/cli/handlers/prepare_environment_handler.py
ftt/cli/handlers/steps/__init__.py
ftt/cli/handlers/steps/database_setup_step.py
ftt/cli/handlers/steps/define_expected_working_directory_step.py
ftt/cli/handlers/steps/define_package_path_step.py
ftt/cli/handlers/steps/first_run_detect_step.py
ftt/cli/handlers/steps/initialize_application_config_step.py
ftt/cli/handlers/steps/portfolio_fields_prompts_step.py
ftt/cli/handlers/steps/portfolio_version_fields_prompts_step.py
ftt/cli/handlers/steps/root_folder_setup_step.py
ftt/cli/handlers/update_portfolio_prompts_handler.py
ftt/cli/plugin.py
ftt/cli/prompt.py
ftt/cli/renderers/__init__.py
ftt/cli/renderers/abstract_renderer.py
ftt/cli/renderers/portfolio_versions/__init__.py
ftt/cli/renderers/portfolio_versions/portfolio_version_details.py
ftt/cli/renderers/portfolio_versions/portfolio_versions_list.py
ftt/cli/renderers/portfolios/__init__.py
ftt/cli/renderers/portfolios/portfolio_details.py
ftt/cli/renderers/portfolios/portfolios_list.py
ftt/cli/renderers/securities/__init__.py
ftt/cli/renderers/securities/securities_list.py
ftt/cli/renderers/weights/__init__.py
ftt/cli/renderers/weights/weights_list.py
ftt/cli/status_bar.py
ftt/cli/token.py
ftt/config/example_portfolio.yml
ftt/config/symbols.yml
ftt/handlers/__init__.py
ftt/handlers/handler/__init__.py
ftt/handlers/handler/abstract_step.py
ftt/handlers/handler/context.py
ftt/handlers/handler/handler.py
ftt/handlers/handler/map_steps.py
ftt/handlers/handler/return_result.py
ftt/handlers/portfolio_associate_securities_hanlder.py
ftt-0.1.0.dist-info/entry_points.txt
ftt-0.1.0.dist-info/LICENSE.md
ftt-0.1.0.dist-info/WHEEL
ftt-0.1.0.dist-info/METADATA
ftt-0.1.0.dist-info/RECORD
